rules_extraction/__init__.py
rules_extraction/plot.py
rules_extraction/rules.py
rules_extraction/utils.py
rules_extraction-0.1.4.dist-info/METADATA
rules_extraction-0.1.4.dist-info/WHEEL
rules_extraction-0.1.4.dist-info/licenses/LICENSE
rules_extraction-0.1.4.dist-info/RECORD
