Metadata-Version: 2.3
Name: rules-extraction
Version: 0.1.4
Summary: Rules extraction for eXplainable AI
Author-email: Arthur Babey <arthur.babey@heig-vd.ch>
License: 3-Clause BSD License
License-File: LICENSE
Keywords: machine learning,xai
Classifier: Intended Audience :: Developers
Classifier: Intended Audience :: Education
Classifier: Intended Audience :: Science/Research
Classifier: License :: OSI Approved :: BSD License
Classifier: Operating System :: MacOS
Classifier: Operating System :: Microsoft :: Windows
Classifier: Operating System :: POSIX
Classifier: Operating System :: Unix
Classifier: Programming Language :: Python :: 3
Classifier: Topic :: Scientific/Engineering
Classifier: Topic :: Scientific/Engineering :: Artificial Intelligence
Classifier: Topic :: Scientific/Engineering :: Mathematics
Requires-Python: >=3.9.0
Requires-Dist: black>=23.9.1
Requires-Dist: build>=1.0.3
Requires-Dist: coverage>=7.3.1
Requires-Dist: flake8>=6.1.0
Requires-Dist: matplotlib>=3.7.3
Requires-Dist: numpy<2.0.0,>=1.17.4
Requires-Dist: pandas==2.0.3
Requires-Dist: pre-commit>=3.4.0
Requires-Dist: scikit-learn>=1.1.3
Requires-Dist: sphinx-autodoc-typehints>=1.22
Requires-Dist: sphinx-rtd-theme>=1.3.0
Requires-Dist: sphinx>=6.2.1
Requires-Dist: torch>=2.0.1
Requires-Dist: torchvision>=0.15.2
